src/main.py
grk-0.0.1.dist-info/METADATA
grk-0.0.1.dist-info/WHEEL
grk-0.0.1.dist-info/entry_points.txt
grk-0.0.1.dist-info/RECORD
